[
  {
    "date": "10.11.2025",
    "title": "День карьеры",
    "location": "актовый зал",
    "description": "Встреча с работодателями и компании-партнеры",
    "link": "https://example.com/career"
  },
  {
    "date": "10.11.2025",
    "title": "Лекция по машинному обучению",
    "location": "ауд. 301",
    "description": "Введение в нейронные сети и глубокое обучение",
    "link": ""
  },
  {
    "date": "11.11.2025",
    "title": "Воркшоп по веб-разработке",
    "location": "компьютерный класс",
    "description": "Практическое занятие по созданию современных веб-приложений",
    "link": ""
  },
  {
    "date": "11.11.2025",
    "title": "Студенческий квиз",
    "location": "актовый зал",
    "description": "Интеллектуальная викторина для студентов",
    "link": ""
  },
  {
    "date": "12.11.2025",
    "title": "Мастер-класс по Python",
    "location": "ауд. 405",
    "description": "Практические примеры работы с Python",
    "link": ""
  },
  {
    "date": "11.11.2025",
    "title": "Киберспортивный турнир",
    "location": "спортивный зал",
    "description": "Турнир по Dota 2 и CS:GO",
    "link": ""
  },
  {
    "date": "15.11.2025",
    "title": "Хакатон VK",
    "location": "главный корпус",
    "description": "48-часовой хакатон от VK",
    "link": "https://vk.com/hackathon"
  }
]

